MANIFEST.in
README.md
setup.py
.servicer/docker_image.yaml
.servicer/services.yaml
servicer/__init__.py
servicer/__main__.py
servicer/config_loader.py
servicer/dependency_grapher.py
servicer/generate_ci_config.py
servicer/git.py
servicer/install-docker-compose.sh
servicer/install-google-cloud-sdk.sh
servicer/logger.py
servicer/run.py
servicer/servicer.py
servicer/token_interpolator.py
servicer/topological_order.py
servicer.egg-info/PKG-INFO
servicer.egg-info/SOURCES.txt
servicer.egg-info/dependency_links.txt
servicer.egg-info/entry_points.txt
servicer.egg-info/requires.txt
servicer.egg-info/top_level.txt
servicer/builtin/__init__.py
servicer/builtin/defaults.yaml
servicer/builtin/auth/__init__.py
servicer/builtin/auth/gcloud.sh
servicer/builtin/auth_adapters/__init__.py
servicer/builtin/auth_adapters/base_auth_adapter.py
servicer/builtin/auth_adapters/dockerhub.py
servicer/builtin/auth_adapters/gcloud.py
servicer/builtin/auth_adapters/packer.py
servicer/builtin/auth_adapters/sonarqube.py
servicer/builtin/ci_adapters/__init__.py
servicer/builtin/ci_adapters/base_ci_adapter.py
servicer/builtin/ci_adapters/bitbucket.py
servicer/builtin/ci_adapters/circleci.py
servicer/builtin/ci_adapters/gitlab.py
servicer/builtin/ci_adapters/jenkins.py
servicer/builtin/service_adapters/__init__.py
servicer/builtin/service_adapters/docker_image.py
servicer/builtin/service_adapters/request_service.py
servicer/builtin/service_adapters/service.py
servicer/builtin/service_adapters/task_service.py
servicer/builtin/service_adapters/artifactory/__init__.py
servicer/builtin/service_adapters/artifactory/artifactory.py
servicer/builtin/service_adapters/aws/__init__.py
servicer/builtin/service_adapters/aws/aws_service.py
servicer/builtin/service_adapters/aws/rds_instance.py
servicer/builtin/service_adapters/aws/s3_bucket.py
servicer/builtin/service_adapters/gcloud/__init__.py
servicer/builtin/service_adapters/gcloud/bucket.py
servicer/builtin/service_adapters/gcloud/docker_image.py
servicer/builtin/service_adapters/gcloud/gcloud_service.py
servicer/builtin/service_adapters/gcloud/kubernetes_cluster.py
servicer/builtin/service_adapters/hashicorp/__init__.py
