Metadata-Version: 2.1
Name: servicer
Version: 0.11.7
Summary: CI/CD Automation Framework
Home-page: https://github.com/wmgroot/servicer
Author: Matt Groot
Author-email: 
License: BSD3
Keywords: ci cd automation environment service
Platform: UNKNOWN
Classifier: Development Status :: 3 - Alpha
Classifier: Topic :: Utilities
Classifier: License :: OSI Approved :: BSD License
Requires-Python: >=3.5
